plottoterminal/__init__.py
plottoterminal/main.py
plottoterminal/lib/__init__.py
plottoterminal/lib/cli.py
plottoterminal/lib/figure.py
plottoterminal/lib/graph.py
plottoterminal/lib/plots.py
plottoterminal/lib/utils.py
plottoterminal-1.0.dist-info/METADATA
plottoterminal-1.0.dist-info/WHEEL
plottoterminal-1.0.dist-info/entry_points.txt
plottoterminal-1.0.dist-info/top_level.txt
plottoterminal-1.0.dist-info/RECORD
