Metadata-Version: 2.1
Name: plottoterminal
Version: 1.0
Summary: Plotting library for the terminal.
Home-page: https://github.com/bitromortac/plottoterminal
Author: bitromortac
Author-email: bitromortac@protonmail.com
License: UNKNOWN
Platform: UNKNOWN
Classifier: Programming Language :: Python :: 3
Classifier: License :: OSI Approved :: MIT License
Classifier: Operating System :: OS Independent
Requires-Dist: wheel
